README.md
streamlit_monaco_yaml/__init__.py
streamlit_monaco_yaml/frontend-build/1045.js
streamlit_monaco_yaml/frontend-build/1045.js.LICENSE.txt
streamlit_monaco_yaml/frontend-build/1045.js.map
streamlit_monaco_yaml/frontend-build/1186.js
streamlit_monaco_yaml/frontend-build/1186.js.LICENSE.txt
streamlit_monaco_yaml/frontend-build/1186.js.map
streamlit_monaco_yaml/frontend-build/1306.js
streamlit_monaco_yaml/frontend-build/1306.js.LICENSE.txt
streamlit_monaco_yaml/frontend-build/1306.js.map
streamlit_monaco_yaml/frontend-build/1314.js
streamlit_monaco_yaml/frontend-build/1314.js.LICENSE.txt
streamlit_monaco_yaml/frontend-build/1314.js.map
streamlit_monaco_yaml/frontend-build/136.js
streamlit_monaco_yaml/frontend-build/136.js.LICENSE.txt
streamlit_monaco_yaml/frontend-build/136.js.map
streamlit_monaco_yaml/frontend-build/1619.js
streamlit_monaco_yaml/frontend-build/1619.js.LICENSE.txt
streamlit_monaco_yaml/frontend-build/1619.js.map
streamlit_monaco_yaml/frontend-build/1904.js
streamlit_monaco_yaml/frontend-build/1904.js.LICENSE.txt
streamlit_monaco_yaml/frontend-build/1904.js.map
streamlit_monaco_yaml/frontend-build/1915.js
streamlit_monaco_yaml/frontend-build/1915.js.LICENSE.txt
streamlit_monaco_yaml/frontend-build/1915.js.map
streamlit_monaco_yaml/frontend-build/1935.js
streamlit_monaco_yaml/frontend-build/1935.js.LICENSE.txt
streamlit_monaco_yaml/frontend-build/1935.js.map
streamlit_monaco_yaml/frontend-build/2045.js
streamlit_monaco_yaml/frontend-build/2045.js.LICENSE.txt
streamlit_monaco_yaml/frontend-build/2045.js.map
streamlit_monaco_yaml/frontend-build/2125.js
streamlit_monaco_yaml/frontend-build/2125.js.LICENSE.txt
streamlit_monaco_yaml/frontend-build/2125.js.map
streamlit_monaco_yaml/frontend-build/2205.js
streamlit_monaco_yaml/frontend-build/2205.js.LICENSE.txt
streamlit_monaco_yaml/frontend-build/2205.js.map
streamlit_monaco_yaml/frontend-build/2273.js
streamlit_monaco_yaml/frontend-build/2273.js.LICENSE.txt
streamlit_monaco_yaml-0.2.0.dist-info/LICENSE.md
streamlit_monaco_yaml-0.2.0.dist-info/METADATA
streamlit_monaco_yaml-0.2.0.dist-info/WHEEL
streamlit_monaco_yaml-0.2.0.dist-info/RECORD
