Metadata-Version: 2.1
Name: streamlit-monaco-yaml
Version: 0.2.0
Summary: Monaco editor component for Streamlit for editing YAML files.
Home-page: https://github.com/semadox/streamlit_monaco_yaml
License: MIT
Author: Skalar Systems
Author-email: contact@skalarsystems.com
Requires-Python: >=3.10,<4.0
Classifier: License :: OSI Approved :: MIT License
Classifier: Programming Language :: Python :: 3
Classifier: Programming Language :: Python :: 3.10
Classifier: Programming Language :: Python :: 3.11
Requires-Dist: streamlit (>=1.26.0,<2.0.0)
Project-URL: Repository, https://github.com/semadox/streamlit_monaco_yaml
